django_postgrespool2/__init__.py
django_postgrespool2/base.py
django_postgrespool2-0.1.0.dist-info/DESCRIPTION.rst
django_postgrespool2-0.1.0.dist-info/METADATA
django_postgrespool2-0.1.0.dist-info/RECORD
django_postgrespool2-0.1.0.dist-info/WHEEL
django_postgrespool2-0.1.0.dist-info/metadata.json
django_postgrespool2-0.1.0.dist-info/top_level.txt
