Metadata-Version: 2.0
Name: django-postgrespool2
Version: 0.1.0
Summary: Postgres Connection Pooling for Django.
Home-page: https://github.com/lcd1232/django-postgrespool2
Author: lcd1232
Author-email: malexey1984@gmail.com
License: MIT
Platform: UNKNOWN
Classifier: Intended Audience :: Developers
Classifier: Natural Language :: English
Classifier: License :: OSI Approved :: MIT License
Classifier: Programming Language :: Python
Classifier: Programming Language :: Python :: 2.7
Requires-Dist: psycopg2
Requires-Dist: sqlalchemy
